ritellm-0.1.7.dist-info/METADATA
ritellm-0.1.7.dist-info/WHEEL
ritellm/__init__.py
ritellm/ritellm.cp39-win_amd64.pyd
ritellm-0.1.7.dist-info/RECORD
