Metadata-Version: 2.4
Name: ritellm
Version: 0.1.7
Requires-Dist: python-dotenv>=1.1.1
Requires-Dist: weave>=0.52.10
Summary: A fast LLM gateway
Requires-Python: >=3.12
